[{"Name":"GPU#00","Index":0,"PlatformId":0,"PlatformId_Index":0,"Type_PlatformId_Index":0,"Platform_Vendor":"NVIDIA","Vendor":"NVIDIA","Vendor_Name":"NVIDIA Corporation","Vendor_Index":0,"Type":"Gpu","Type_Index":0,"Type_Codec_Index":0,"Type_Mineable_Index":0,"Type_Vendor_Index":0,"BusId_Index":0,"BusId_Type_Index":0,"BusId_Type_Vendor_Index":0,"BusId_Type_Mineable_Index":0,"BusId_Vendor_Index":0,"OpenCL":{"DeviceIndex":0,"Name":"NVIDIA GeForce GTX 1650","Architecture":"Turing","Type":"Gpu","Vendor":"NVIDIA Corporation","GlobalMemSize":4294639616,"GlobalMemSizeGB":4,"MaxComputeUnits":16,"PlatformVersion":"OpenCL 3.0 CUDA 12.2.138","DriverVersion":"537.13","PCIBusId":"01:00","DeviceCapability":"7.5","CardId":-1},"Codec":"CUDA","Model":"GTX1650","Model_Base":"GTX1650","Model_Name":"GeForce GTX 1650","InstanceId":"PCI\\VEN_10DE\u0026DEV_1F91\u0026SUBSYS_86D5103C\u0026REV_A1\\4\u002624648110\u00260\u00260009","CardId":-1,"BusId":"01:00","SubId":"1F91","IsLHR":false,"GpuGroup":"","Data":{"AdapterId":0,"Utilization":9,"UtilizationMem":1,"Clock":510,"ClockMem":405,"FanSpeed":null,"Temperature":46,"PowerDraw":1.73,"PowerLimit":null,"PowerLimitPercent":0,"PowerMaxLimit":50,"PowerDefaultLimit":50,"Pstate":"P8","Method":"smi"},"DataMax":{"Clock":510,"ClockMem":405,"Temperature":46,"FanSpeed":0,"PowerDraw":1.73}},{"Name":"GPU#01","Index":1,"PlatformId":1,"PlatformId_Index":0,"Type_PlatformId_Index":0,"Platform_Vendor":"AMD","Vendor":"AMD","Vendor_Name":"Advanced Micro Devices, Inc.","Vendor_Index":0,"Type":"Gpu","Type_Index":1,"Type_Codec_Index":0,"Type_Mineable_Index":1,"Type_Vendor_Index":0,"BusId_Index":1,"BusId_Type_Index":1,"BusId_Type_Vendor_Index":0,"BusId_Type_Mineable_Index":1,"BusId_Vendor_Index":0,"OpenCL":{"DeviceIndex":0,"Name":"AMD Radeon(TM) Vega 8 Graphics","Architecture":"gfx902","Type":"Gpu","Vendor":"Advanced Micro Devices, Inc.","GlobalMemSize":10755768320,"GlobalMemSizeGB":10,"MaxComputeUnits":8,"PlatformVersion":"OpenCL 2.1 AMD-APP (3004.4)","DriverVersion":"3004.4 (PAL,HSAIL)","PCIBusId":"05:00","DeviceCapability":"GCN50","CardId":-1},"Codec":"OpenCL","Model":"Vega8","Model_Base":"Vega8","Model_Name":"Radeon Vega 8","InstanceId":"PCI\\VEN_1002\u0026DEV_15D8\u0026SUBSYS_86D5103C\u0026REV_C2\\4\u0026514E054\u00260\u00260041","CardId":-1,"BusId":"05:00","SubId":"noid","IsLHR":false,"GpuGroup":"","Data":{"AdapterId":0,"Utilization":0,"UtilizationMem":0,"Clock":0,"ClockMem":1200,"FanSpeed":511,"Temperature":70,"PowerDraw":19,"PowerLimit":0,"PowerLimitPercent":0,"PowerMaxLimit":0,"PowerDefaultLimit":0,"Pstate":"","Method":"odvii8"},"DataMax":{"Clock":0,"ClockMem":1200,"Temperature":70,"FanSpeed":511,"PowerDraw":19}},{"Name":"CPU#00","Index":2,"Vendor":"AMD","Vendor_Name":"AuthenticAMD","Type_PlatformId_Index":0,"Type_Vendor_Index":0,"Type":"Cpu","Type_Index":0,"Type_Mineable_Index":0,"Type_Codec_Index":0,"Model":"CPU","Model_Base":"CPU","Model_Name":"AMD Ryzen 5 3550H with Radeon Vega Mobile Gfx","Features":["bmi2","adx","abm","sha","avx","sse","avx2","iszen","ssse3","fma3","mmx","sse4a","sse2","bmi1","sse42","x64","aes","sse3","rdrand","sse41"],"Data":{"Cores":4,"Threads":8,"CacheL3":4096,"Clock":3078,"Utilization":21,"PowerDraw":8,"Temperature":50,"Method":"lhm"},"DataMax":{"Clock":3078,"Utilization":21,"PowerDraw":8,"Temperature":50}}]
